rusty_manga_image_translator/__init__.py
rusty_manga_image_translator/rusty_manga_image_translator.abi3.so
rusty_manga_image_translator.libs/libcrypto-ef58def3.so.3
rusty_manga_image_translator.libs/libcudnn-3b68ea68.so.9
rusty_manga_image_translator.libs/libgomp-115302e4.so.1
rusty_manga_image_translator.libs/libonnxruntime_providers_cuda.so
rusty_manga_image_translator.libs/libonnxruntime_providers_shared.so
rusty_manga_image_translator.libs/libonnxruntime_providers_tensorrt.so
rusty_manga_image_translator.libs/libopencv_core-8baa4de0.so.4.5d
rusty_manga_image_translator.libs/libopencv_imgproc-33dba9de.so.4.5d
rusty_manga_image_translator.libs/libssl-660a6abe.so.3
rusty_manga_image_translator.libs/libtbb-b87fa093.so.2
rusty_manga_image_translator-0.12.1.dist-info/METADATA
rusty_manga_image_translator-0.12.1.dist-info/WHEEL
rusty_manga_image_translator-0.12.1.dist-info/RECORD
