Metadata-Version: 2.4
Name: rusty-manga-image-translator
Version: 0.12.1
Classifier: Programming Language :: Python :: 3
Classifier: Programming Language :: Rust
Classifier: Operating System :: OS Independent
Requires-Dist: numpy>1
Summary: Rust implementation of manga-image-translator with py-bindings
Keywords: manga,image-processing,rust,python,translator
Author-email: Frederik <termite_pilgrim04@icloud.com>
Requires-Python: >=3.9
Project-URL: Homepage, https://github.com/frederik-uni/manga-image-translator-rust
Project-URL: Repository, https://github.com/frederik-uni/manga-image-translator-rust
Project-URL: Issues, https://github.com/frederik-uni/manga-image-translator-rust/issues
Project-URL: Changelog, https://github.com/frederik-uni/manga-image-translator-rust/blob/master/CHANGELOG.md
